{"win": 100, "free": 25, "iphone": 36, "click": 21, "now": 69, "your": 108, "bank": 13, "account": 6, "compromised": 23, "verify": 97, "congratulations": 24, "1000": 1, "prize": 76, "reply": 77, "yes": 105, "pata": 72, "mpesa": 58, "50000": 4, "bila": 16, "malipo": 53, "tuma": 90, "nambari": 63, "umeshinda": 91, "piga": 74, "kura": 46, "na": 62, "upate": 94, "zawadi": 109, "are": 9, "you": 107, "coming": 22, "to": 88, "the": 86, "meeting": 55, "tomorrow": 89, "hi": 30, "mom": 57, "ill": 34, "be": 14, "home": 32, "by": 18, "6pm": 5, "habari": 27, "yako": 104, "je": 38, "utakuwa": 96, "shuleni": 82, "kesho": 42, "mama": 54, "nitakuwa": 67, "nyumbani": 70, "saa": 78, "nne": 68, "usiku": 95, "umwambie": 92, "mwanawe": 61, "atumie": 11, "pesa": 73, "yake": 103, "yote": 106, "hii": 31, "ni": 64, "fursa": 26, "ya": 102, "maisha": 52, "bonyeza": 17, "hapa": 28, "akaunti": 7, "imefungwa": 35, "thibitisha": 87, "sasa": 81, "unajisikiaje": 93, "leo": 50, "nitakuja": 65, "baada": 12, "kazi": 41, "asante": 10, "kwa": 47, "kunifundisha": 44, "jina": 39, "langu": 49, "iko": 33, "tayari": 85, "pin": 75, "haraka": 29, "itaisha": 37, "15001": 3, "kupata": 45, "salio": 80, "siku": 83, "nzuri": 71, "kuanza": 43, "biashara": 15, "winner": 101, "lako": 48, "12345": 2, "mtoto": 60, "wako": 99, "amefika": 8, "salama": 79, "link": 51, "mkopo": 56, "wa": 98, "nitakuletea": 66, "chakula": 20, "jioni": 40, "simu": 84, "mpya": 59, "call": 19, "0800": 0}